{
  "project_info": {
    "project_number": "754205174001",
    "project_id": "finedu-app-e5e22",
    "storage_bucket": "finedu-app-e5e22.firebasestorage.app"
  },
  "client": [
    {
      "client_info": {
        "mobilesdk_app_id": "1:754205174001:android:561dd84c148c2b1b016150",
        "android_client_info": {
          "package_name": "com.finedu.app"
        }
      },
      "oauth_client": [],
      "api_key": [
        {
          "current_key": "AIzaSyBR9azFb9E6PUOSKU30n_er9NezP-UYT3c"
        }
      ],
      "services": {
        "appinvite_service": {
          "other_platform_oauth_client": []
        }
      }
    }
  ],
  "configuration_version": "1"
}